LICENSE
MANIFEST.in
README.md
dev-requirements.txt
requirements.txt
setup.py
mapping/__init__.py
mapping/_version.py
mapping/mappings.py
mapping/plot.py
mapping/util.py
mapping.egg-info/PKG-INFO
mapping.egg-info/SOURCES.txt
mapping.egg-info/dependency_links.txt
mapping.egg-info/not-zip-safe
mapping.egg-info/requires.txt
mapping.egg-info/top_level.txt
mapping/tests/__init__.py
mapping/tests/test_mappings.py
mapping/tests/test_util.py
mapping/tests/data/CME-CLF2017.csv
mapping/tests/data/CME-CLX2016.csv
mapping/tests/data/CME-CLZ2016.csv
mapping/tests/data/CME-FVU2014.csv
mapping/tests/data/CME-FVZ2014.csv
mapping/tests/data/CME_CL_meta.csv