Metadata-Version: 1.0
Name: mapping
Version: 0.1.6
Summary: Mappings for generic and tradeable futures instruments
Home-page: https://github.com/MatthewGilbert/mapping
Author: Matthew Gilbert
Author-email: matthew.gilbert12@gmail.com
License: MIT
Platform: any
